repo_ranger/__init__.py
repo_ranger/repo_ranger.py
repo_ranger-0.1.1.data/data/man/man1/repo_ranger.1
tests/__init__.py
tests/test_clone.py
tests/test_filter_repos.py
tests/test_help.py
tests/test_init.py
tests/test_list.py
tests/test_pull.py
repo_ranger-0.1.1.dist-info/METADATA
repo_ranger-0.1.1.dist-info/WHEEL
repo_ranger-0.1.1.dist-info/entry_points.txt
repo_ranger-0.1.1.dist-info/top_level.txt
repo_ranger-0.1.1.dist-info/RECORD
