Metadata-Version: 2.1
Name: repo-ranger
Version: 0.1.1
Summary: A command-line tool for managing a set of Git repositories
Home-page: UNKNOWN
Author: Panagiotis Nezis
Author-email: pnezis@gmail.com
License: UNKNOWN
Platform: UNKNOWN
Classifier: Programming Language :: Python :: 3
Classifier: License :: OSI Approved :: MIT License
Classifier: Operating System :: OS Independent
Requires-Dist: PyYAML
Requires-Dist: termcolor
